AUTHORS.rst
LICENSE.txt
MANIFEST.in
README.rst
VERSION.txt
setup.cfg
setup.py
wpa_xhtml2pdf.egg-info/PKG-INFO
wpa_xhtml2pdf.egg-info/SOURCES.txt
wpa_xhtml2pdf.egg-info/dependency_links.txt
wpa_xhtml2pdf.egg-info/entry_points.txt
wpa_xhtml2pdf.egg-info/requires.txt
wpa_xhtml2pdf.egg-info/top_level.txt
xhtml2pdf/__init__.py
xhtml2pdf/charts.py
xhtml2pdf/context.py
xhtml2pdf/default.py
xhtml2pdf/document.py
xhtml2pdf/files.py
xhtml2pdf/paragraph.py
xhtml2pdf/parser.py
xhtml2pdf/pdf.py
xhtml2pdf/pisa.py
xhtml2pdf/reportlab_paragraph.py
xhtml2pdf/tables.py
xhtml2pdf/tags.py
xhtml2pdf/util.py
xhtml2pdf/wsgi.py
xhtml2pdf/xhtml2pdf_reportlab.py
xhtml2pdf/builders/__init__.py
xhtml2pdf/builders/grid.py
xhtml2pdf/builders/signs.py
xhtml2pdf/builders/watermarks.py
xhtml2pdf/config/__init__.py
xhtml2pdf/config/httpconfig.py
xhtml2pdf/w3c/__init__.py
xhtml2pdf/w3c/css.py
xhtml2pdf/w3c/cssDOMElementInterface.py
xhtml2pdf/w3c/cssParser.py
xhtml2pdf/w3c/cssSpecial.py