Metadata-Version: 2.1
Name: wpa-xhtml2pdf
Version: 0.2.8.2
Summary: PDF generator using HTML and CSS
Home-page: https://github.com/WePlayAgain/xhtml2pdf.git
Download-URL: https://github.com/WePlayAgain/xhtml2pdf/archive/refs/tags/v0.2.8.2.tar.gz
Maintainer: Mib
Maintainer-email: mib@weplayagain.com
License: Apache License 2.0
Keywords: PDF,HTML,XHTML,XML,CSS
Classifier: License :: OSI Approved :: Apache Software License
Classifier: Development Status :: 4 - Beta
Classifier: Environment :: Console
Classifier: Environment :: Other Environment
Classifier: Intended Audience :: Developers
Classifier: Intended Audience :: System Administrators
Classifier: Natural Language :: English
Classifier: Operating System :: OS Independent
Classifier: Programming Language :: Python :: 3
Classifier: Programming Language :: Python :: 3.6
Classifier: Programming Language :: Python :: 3.7
Classifier: Programming Language :: Python :: 3.8
Classifier: Programming Language :: Python :: 3.9
Classifier: Programming Language :: Python :: 3.10
Classifier: Topic :: Documentation
Classifier: Topic :: Multimedia
Classifier: Topic :: Office/Business
Classifier: Topic :: Printing
Classifier: Topic :: Text Processing
Classifier: Topic :: Text Processing :: Filters
Classifier: Topic :: Text Processing :: Fonts
Classifier: Topic :: Text Processing :: General
Classifier: Topic :: Text Processing :: Indexing
Classifier: Topic :: Text Processing :: Markup
Classifier: Topic :: Text Processing :: Markup :: HTML
Classifier: Topic :: Text Processing :: Markup :: XML
Classifier: Topic :: Utilities
License-File: LICENSE.txt
License-File: AUTHORS.rst
